wikiwikiweb/__init__.py
wikiwikiweb/admin.py
wikiwikiweb/apps.py
wikiwikiweb/context_processors.py
wikiwikiweb/forms.py
wikiwikiweb/models.py
wikiwikiweb/urls.py
wikiwikiweb/views.py
wikiwikiweb/fixtures/basic-db.json
wikiwikiweb/migrations/0001_initial.py
wikiwikiweb/migrations/0002_historicalwikispace_homepage_wikispace_homepage.py
wikiwikiweb/migrations/0003_historicalwikipage_created_by_and_more.py
wikiwikiweb/migrations/__init__.py
wikiwikiweb/templates/registration/login.html
wikiwikiweb/templates/wiki/__base.html
wikiwikiweb/templates/wiki/home.html
wikiwikiweb/templates/wiki/mywiki.html
wikiwikiweb/templates/wiki/search.html
wikiwikiweb/templates/wiki/space.html
wikiwikiweb/templates/wiki/space_select.html
wikiwikiweb/templates/wiki/user.html
wikiwikiweb/templates/wiki/wiki_page.html
wikiwikiweb/templates/wiki/wiki_page_archive.html
wikiwikiweb/templates/wiki/wiki_page_create.html
wikiwikiweb/templates/wiki/wiki_page_edit.html
wikiwikiweb/templatetags/__init__.py
wikiwikiweb/templatetags/wiki_extras.py
django_wikiwikiweb-1.0.1.dist-info/METADATA
django_wikiwikiweb-1.0.1.dist-info/WHEEL
django_wikiwikiweb-1.0.1.dist-info/licenses/LICENSE
django_wikiwikiweb-1.0.1.dist-info/RECORD
