Metadata-Version: 2.4
Name: django-wikiwikiweb
Version: 1.0.1
Summary: A Django WikiWikiWeb app
Project-URL: Documentation, https://django-wikiwikiweb.readthedocs.io/
Project-URL: Homepage, https://github.com/simonharris/django-wikiwikiweb
Project-URL: Issues, https://github.com/simonharris/django-wikiwikiweb/issues
Project-URL: Source, https://github.com/simonharris/django-wikiwikiweb
Author-email: Simon Harding <github@pointbeing.net>
License-File: LICENSE
Classifier: License :: OSI Approved :: MIT License
Classifier: Operating System :: OS Independent
Classifier: Programming Language :: Python :: 3
Requires-Python: >=3.8
Requires-Dist: django-bootstrap5>=24.2
Requires-Dist: django-markdownify>=0.9.5
Requires-Dist: django-simple-history>=3.7.0
Requires-Dist: django>=5.0.6
